lib16univin/__init__.py
lib16univin/lib16univin_data.py
sm16univin-1.0.4.dist-info/LICENSE
sm16univin-1.0.4.dist-info/METADATA
sm16univin-1.0.4.dist-info/WHEEL
sm16univin-1.0.4.dist-info/top_level.txt
sm16univin-1.0.4.dist-info/RECORD
